README
setup.py
virtstrap_local/__init__.py
virtstrap_local/runner.py
virtstrap_local.egg-info/PKG-INFO
virtstrap_local.egg-info/SOURCES.txt
virtstrap_local.egg-info/dependency_links.txt
virtstrap_local.egg-info/entry_points.txt
virtstrap_local.egg-info/not-zip-safe
virtstrap_local.egg-info/requires.txt
virtstrap_local.egg-info/top_level.txt
virtstrap_local/commands/__init__.py
virtstrap_local/commands/clean.py
virtstrap_local/commands/commands.py
virtstrap_local/commands/environment.py
virtstrap_local/commands/install.py