Metadata-Version: 1.0
Name: virtstrap-local
Version: 0.3.4
Summary: virtstrap's project local commands
Home-page: UNKNOWN
Author: Reuven V. Gonzales
Author-email: reuven@tobetter.us
License: UNKNOWN
Platform: UNKNOWN
